{
  "version": "6.0",
  "nxVersion": "21.1.3",
  "pathMappings": {},
  "nxJsonPlugins": [],
  "fileMap": {
    "projectFileMap": {
      "@reefmix/rxjs-devtools-chrome-extension": [
        {
          "file": "packages/rxjs-devtools-chrome-extension/.gitignore",
          "hash": "1040494916239047768"
        },
        {
          "file": "packages/rxjs-devtools-chrome-extension/README.md",
          "hash": "11050586184205246340"
        },
        {
          "file": "packages/rxjs-devtools-chrome-extension/Step1.md",
          "hash": "13161791028521367567"
        },
        {
          "file": "packages/rxjs-devtools-chrome-extension/package.json",
          "hash": "17678311518720537626",
          "deps": [
            "npm:@types/react",
            "npm:@types/react-dom",
            "npm:copy-webpack-plugin",
            "npm:eslint",
            "npm:ts-loader",
            "npm:typescript",
            "npm:vitest",
            "npm:webpack",
            "npm:webpack-cli",
            "npm:react",
            "npm:react-dom",
            "npm:rxjs"
          ]
        },
        {
          "file": "packages/rxjs-devtools-chrome-extension/public/icons/.keep",
          "hash": "3244421341483603138"
        },
        {
          "file": "packages/rxjs-devtools-chrome-extension/public/icons/icon128.png",
          "hash": "12033913341753796465"
        },
        {
          "file": "packages/rxjs-devtools-chrome-extension/public/icons/icon16.png",
          "hash": "17344610407697111907"
        },
        {
          "file": "packages/rxjs-devtools-chrome-extension/public/icons/icon32.png",
          "hash": "9226103842974270422"
        },
        {
          "file": "packages/rxjs-devtools-chrome-extension/public/icons/icon48.png",
          "hash": "9709470482958883683"
        },
        {
          "file": "packages/rxjs-devtools-chrome-extension/rxjs-devtools-chrome-extension.zip",
          "hash": "3347210653409844835"
        },
        {
          "file": "packages/rxjs-devtools-chrome-extension/src/background.ts",
          "hash": "18039906214550416366"
        },
        {
          "file": "packages/rxjs-devtools-chrome-extension/src/content.ts",
          "hash": "16949927368681714936"
        },
        {
          "file": "packages/rxjs-devtools-chrome-extension/src/devtools.html",
          "hash": "12010588505341187861"
        },
        {
          "file": "packages/rxjs-devtools-chrome-extension/src/devtools.tsx",
          "hash": "6348537815243703980"
        },
        {
          "file": "packages/rxjs-devtools-chrome-extension/src/manifest.json",
          "hash": "1405742402119163235"
        },
        {
          "file": "packages/rxjs-devtools-chrome-extension/src/popup/popup.html",
          "hash": "5768492831709518008"
        },
        {
          "file": "packages/rxjs-devtools-chrome-extension/src/popup/popup.tsx",
          "hash": "2853811075747205576"
        },
        {
          "file": "packages/rxjs-devtools-chrome-extension/tsconfig.json",
          "hash": "14587856016958784999"
        },
        {
          "file": "packages/rxjs-devtools-chrome-extension/webpack.config.js",
          "hash": "16875652408657347635"
        }
      ],
      "@reefmix/rxjs-devtools-react": [
        {
          "file": "packages/rxjs-devtools-react/README.md",
          "hash": "14901879733725652709"
        },
        {
          "file": "packages/rxjs-devtools-react/Step1.md",
          "hash": "12863726450594957495"
        },
        {
          "file": "packages/rxjs-devtools-react/package.json",
          "hash": "1531904610476432703",
          "deps": [
            "npm:react",
            "npm:rxjs",
            "npm:@types/react",
            "npm:eslint",
            "npm:typescript",
            "npm:vite",
            "npm:vitest",
            "npm:redux-observable"
          ]
        },
        {
          "file": "packages/rxjs-devtools-react/src/index.ts",
          "hash": "11838323165111272706"
        },
        {
          "file": "packages/rxjs-devtools-react/tsconfig.json",
          "hash": "4702474528471043699"
        },
        {
          "file": "packages/rxjs-devtools-react/vite.config.ts",
          "hash": "4251846943609107765"
        }
      ]
    },
    "nonProjectFiles": [
      {
        "file": ".changeset/README.md",
        "hash": "4888845876018830777"
      },
      {
        "file": ".changeset/config.json",
        "hash": "13777462855751112962"
      },
      {
        "file": ".cursor/rules/cursor-rules.mdc",
        "hash": "4190139611151030560"
      },
      {
        "file": ".gitignore",
        "hash": "1040494916239047768"
      },
      {
        "file": ".yarn/install-state.gz",
        "hash": "15390702937338796619"
      },
      {
        "file": ".yarnrc.yml",
        "hash": "9773565372686775399"
      },
      {
        "file": "README.md",
        "hash": "1709789576590121853"
      },
      {
        "file": "package.json",
        "hash": "9394750024389808572"
      },
      {
        "file": "release-beta.sh",
        "hash": "8842352770044785508"
      },
      {
        "file": "yarn.lock",
        "hash": "5311033006054671750"
      }
    ]
  }
}